{
  "sorted_middleware": [],
  "middleware": {
    "/": {
      "files": [
        "server/edge/chunks/_7d9b4a52._.js",
        "server/edge/chunks/[root-of-the-server]__f2b15f93._.js",
        "server/edge/chunks/turbopack-edge-wrapper_574eb55e.js"
      ],
      "name": "middleware",
      "page": "/",
      "matchers": [
        {
          "regexp": "/:nextData(_next/data/[^/]{1,})?/employees/:path*{(\\\\.json)}?",
          "originalSource": "/employees/:path*"
        },
        {
          "regexp": "/:nextData(_next/data/[^/]{1,})?/projects/:path*{(\\\\.json)}?",
          "originalSource": "/projects/:path*"
        },
        {
          "regexp": "/:nextData(_next/data/[^/]{1,})?/invoices/:path*{(\\\\.json)}?",
          "originalSource": "/invoices/:path*"
        }
      ],
      "wasm": [],
      "assets": [],
      "env": {
        "__NEXT_BUILD_ID": "development",
        "NEXT_SERVER_ACTIONS_ENCRYPTION_KEY": "KJZEb3sOYCM3Dw/C46EZV/olDstR9gf2Tj4j+Ndo6TE=",
        "__NEXT_PREVIEW_MODE_ID": "279fe4f9ab30ae1e159a354ad0f3fece",
        "__NEXT_PREVIEW_MODE_ENCRYPTION_KEY": "b681a9406cc84dead5f3eb7449da950d80a00958c36222a02ba9e2e0e017a356",
        "__NEXT_PREVIEW_MODE_SIGNING_KEY": "4d9e87b591e9bb0e5c4050ed4298458e76bb58d662eedb78ec8a3c8cf76aa6a0"
      }
    }
  },
  "instrumentation": null,
  "functions": {}
}